trabalho1/parte3/memoria_dados/memoria_dados.v
module memoria_dados(
    input wire writeEnable,
    input wire[7:0] endereco,
    input reg[7:0] dadoEntrada,
    input wire clk,
    output reg[7:0] dadoSaida
);

    // Cria a memória (Matriz)
    reg[7:0] memoria[0:255];

    always @(posedge clk)
    begin
        if (writeEnable == 1) 
        begin
            memoria[endereco] = dadoEntrada;
        end

        dadoSaida = memoria[endereco];
    end
endmodule

trabalho1/modulos/ula/ula.v
module ula 
(
    input wire[7:0] A,
    input wire[7:0] B,
    input wire[3:0] Seletor,
    output wire[7:0] S
);

    assign S = (Seletor == 4'b0000) ? ~A : 
    (Seletor == 4'b0001) ? (A & B) :  // AND
    (Seletor == 4'b0010) ? (A | B) :  // OR
    (Seletor == 4'b0011) ? (A ^ B) :  // XOR
    (Seletor == 4'b0100) ? (A + B) :  // ADD
    (Seletor == 4'b0101) ? (A - B) :  // SUB
    (Seletor == 4'b0110) ? (A << B) :  // SLR
    (Seletor == 4'b0111) ? (A >> B) :  // SRR
    (Seletor == 4'b1000) ? (A * B) :  // MUL
    (Seletor == 4'b1001) ? ((A << (B % 8'd8)) | (A >> (8'd8 - (B % 8'd8)))) :  // ROL
    8'b0;

endmodule

trabalho1/parte4/redux/banco_reg.v
module banco_reg (
    input wire clk, write_enable, 
    input wire[1:0] r_a, r_b, write_addr,
    input wire[7:0] write_data,
    output wire[7:0] a, b
);

reg[7:0] regs[0:4];

initial begin
    regs[0] = 8'b00000000;
    regs[1] = 8'b00000000;
    regs[2] = 8'b00000000;
    regs[3] = 8'b00000000;
end

always @(posedge clk) begin
    if (write_enable) begin
        regs[write_addr] <= write_data;
    end
end

assign a = regs[r_a];
assign b = regs[r_b];

endmodule

trabalho1/parte4/memoria_controle/memoria_controle.v
module memoria_controle (
    input wire[3:0] opcode,
    output reg[3:0] ula,
    output reg b_mx, j_mx, r_mx, se_mx, d_mx, we, re
);

always @(opcode) begin
    case (opcode)
        4'b0000: begin b_mx = 1;           r_mx = 0;                                     we = 0; re = 0; end
        4'b0001: begin b_mx = 0; j_mx = 1;                                               we = 0; re = 0; end
        4'b0010: begin b_mx = 0; j_mx = 0; r_mx = 0;            d_mx = 0;                we = 0; re = 1; end
        4'b0011: begin b_mx = 0; j_mx = 0; r_mx = 0;                                     we = 1; re = 0; end
        4'b0100: begin b_mx = 0; j_mx = 0; r_mx = 1; se_mx = 1; d_mx = 1; ula = 4'b0100; we = 0; re = 1; end
        4'b0101: begin b_mx = 0; j_mx = 0; r_mx = 1; se_mx = 1; d_mx = 1; ula = 4'b0101; we = 0; re = 1; end
        4'b0110: begin b_mx = 0; j_mx = 0; r_mx = 0; se_mx = 0; d_mx = 1; ula = 4'b1000; we = 0; re = 1; end
        4'b0111: begin b_mx = 0; j_mx = 0; r_mx = 0; se_mx = 0; d_mx = 1; ula = 4'b1001; we = 0; re = 1; end
        4'b1000: begin b_mx = 0; j_mx = 0; r_mx = 0; se_mx = 0; d_mx = 1; ula = 4'b0000; we = 0; re = 1; end
        4'b1001: begin b_mx = 0; j_mx = 0; r_mx = 0; se_mx = 0; d_mx = 1; ula = 4'b0001; we = 0; re = 1; end
        4'b1010: begin b_mx = 0; j_mx = 0; r_mx = 0; se_mx = 0; d_mx = 1; ula = 4'b0010; we = 0; re = 1; end
        4'b1011: begin b_mx = 0; j_mx = 0; r_mx = 0; se_mx = 0; d_mx = 1; ula = 4'b0011; we = 0; re = 1; end
        4'b1100: begin b_mx = 0; j_mx = 0; r_mx = 0; se_mx = 0; d_mx = 1; ula = 4'b0100; we = 0; re = 1; end
        4'b1101: begin b_mx = 0; j_mx = 0; r_mx = 0; se_mx = 0; d_mx = 1; ula = 4'b0101; we = 0; re = 1; end
        4'b1110: begin b_mx = 0; j_mx = 0; r_mx = 0; se_mx = 0; d_mx = 1; ula = 4'b0110; we = 0; re = 1; end
        4'b1111: begin b_mx = 0; j_mx = 0; r_mx = 0; se_mx = 0; d_mx = 1; ula = 4'b0111; we = 0; re = 1; end
    endcase
end

    
endmodule

trabalho1/parte4/redux/memoria_instrucoes.v
module memoria_instrucoes #(
    parameter ALG = 1
) (
    input wire[7:0] endereco,
    output wire[7:0] instrucao
);

    // Cria a memória (Matriz)
    reg[7:0] memoria[0:255];

    // Inicializa a memória com as instrucoes passadas
    initial 
    begin
        if (ALG == 1) begin
            memoria[0] = 8'b10110000;
            memoria[1] = 8'b10110101;
            memoria[2] = 8'b10111010;
            memoria[3] = 8'b10111111;
            memoria[4] = 8'b01000011;
            memoria[5] = 8'b11000100;
            memoria[6] = 8'b10110000;
            memoria[7] = 8'b00110100;
            memoria[8] = 8'b01000111;
            memoria[9] = 8'b01000011;
            memoria[10] = 8'b11001100;
            memoria[11] = 8'b11001000;
            memoria[12] = 8'b01001000;
            memoria[13] = 8'b11101000;
            memoria[14] = 8'b11001000;
            memoria[15] = 8'b01001111;
            memoria[16] = 8'b00111000;
            memoria[17] = 8'b10110000;
            memoria[18] = 8'b10111010;
            memoria[19] = 8'b11011001;
            memoria[20] = 8'b01000101;
            memoria[21] = 8'b11100001;
            memoria[22] = 8'b00010010;
            memoria[23] = 8'b00011100;
            memoria[24] = 8'b01000000;
            memoria[25] = 8'b00001000;
            memoria[26] = 8'b11001001;
            memoria[27] = 8'b10110000;
            memoria[28] = 8'b11001110;
            memoria[29] = 8'b01000001;
            memoria[30] = 8'b00010010;
            memoria[31] = 8'b00011000;
            memoria[32] = 8'b00100100;
            memoria[33] = 8'b11000110;
            memoria[34] = 8'b00110111;
            memoria[35] = 8'b11011110;
            memoria[36] = 8'b11001000;
            memoria[37] = 8'b10110000;
            memoria[38] = 8'b00100100;
            memoria[39] = 8'b00011000;
        end else if (ALG == 2) begin
            memoria[0] = 8'b10110000;
            memoria[1] = 8'b10110101;
            memoria[2] = 8'b10111010;
            memoria[3] = 8'b10111111;
            memoria[4] = 8'b01000101;
            memoria[5] = 8'b00110001;
            memoria[6] = 8'b01010001;
            memoria[7] = 8'b11001000;
            memoria[8] = 8'b01010110;
            memoria[9] = 8'b11100010;
            memoria[10] = 8'b11000100;
            memoria[11] = 8'b10110000;
            memoria[12] = 8'b01000111;
            memoria[13] = 8'b11000100;
            memoria[14] = 8'b01010110;
            memoria[15] = 8'b00110100;
            memoria[16] = 8'b01000010;
            memoria[17] = 8'b11001100;
            memoria[18] = 8'b01010001;
            memoria[19] = 8'b00111100;
            memoria[20] = 8'b10111010;
            memoria[21] = 8'b10110000;
            memoria[22] = 8'b00100100;
            memoria[23] = 8'b01000100;
            memoria[24] = 8'b11100000;
            memoria[25] = 8'b01010100;
            memoria[26] = 8'b00010010;
            memoria[27] = 8'b00011010;
            memoria[28] = 8'b11010110;
            memoria[29] = 8'b00000100;
            memoria[30] = 8'b10110000;
            memoria[31] = 8'b01000001;
            memoria[32] = 8'b11001000;
            memoria[33] = 8'b00100100;
            memoria[34] = 8'b00010010;
            memoria[35] = 8'b00011000;
            memoria[36] = 8'b01110110;
            memoria[37] = 8'b11110000;
            memoria[38] = 8'b10010001;
            memoria[39] = 8'b10111111;
            memoria[40] = 8'b11001100;
            memoria[41] = 8'b10110000;
            memoria[42] = 8'b00010010;
            memoria[43] = 8'b00011000;
            memoria[44] = 8'b01000100;
            memoria[45] = 8'b11100000;
            memoria[46] = 8'b01011111;
            memoria[47] = 8'b00001100;
            memoria[48] = 8'b01100110;
            memoria[49] = 8'b10110000;
            memoria[50] = 8'b00010010;
            memoria[51] = 8'b00011000;
            memoria[52] = 8'b01000010;
            memoria[53] = 8'b00101100;
            memoria[54] = 8'b01010001;
            memoria[55] = 8'b00110100;
            memoria[56] = 8'b11001110;
            memoria[57] = 8'b11011100;
            memoria[58] = 8'b00110111;
            memoria[59] = 8'b00011000;
        end
        
    end

    assign instrucao = memoria[endereco];

endmodule

trabalho1/parte4/redux/contador_de_programa.v
module contador_de_programa (
    input wire[7:0] entrada, 
    input wire clk,
    output reg[7:0] saida
);

initial begin
    saida = 0;
end


always @(posedge clk) begin
    saida <= entrada;
end
    
endmodule

trabalho1/modulos/next_pc/next_pc.v
module next_pc (
    input wire jmx, bmx, zero_flag,
    input wire[7:0] curPC, imm, b,
    output wire[7:0] pc
);
    assign pc = (bmx & zero_flag) ? b :
                jmx ? curPC + imm:
                curPC + 8'd1;
endmodule

trabalho1/parte4/redux/redux.v
module redux (
    input wire clk
);
    wire[7:0] cur_pc, n_pc, imm_extended, a, b, instrucao, write_data, ula_out, data_out, b_ula;
    wire[3:0] ula_sel, imm, opcode;
    wire[1:0] r_a, r_b;
    wire b_mx, j_mx, r_mx, se_mx, d_mx, we, re, zero_flag;

    assign opcode = instrucao[7:4];
    assign imm = instrucao[3:0];
    assign r_a = r_mx ? 2'b00 : instrucao[3:2];
    assign r_b = instrucao[1:0];
    assign imm_extended = { {4{imm[3]}} , imm};
    assign write_data = d_mx ? ula_out : data_out;
    assign b_ula = se_mx ? imm_extended : b;
    assign zero_flag = (a == 8'b00000000) ? 1 : 0;

    next_pc NPC(.jmx(j_mx), .bmx(b_mx), .curPC(cur_pc), .imm(imm_extended), .b(b), .pc(n_pc), .zero_flag(zero_flag));

    contador_de_programa PC(.entrada(n_pc), .clk(clk), .saida(cur_pc));
    memoria_instrucoes MEI(.endereco(cur_pc), .instrucao(instrucao));
    memoria_controle MEC(.opcode(opcode), .ula(ula_sel), .b_mx(b_mx), .j_mx(j_mx), .r_mx(r_mx), .se_mx(se_mx), .d_mx(d_mx), .we(we), .re(re));
    banco_reg BRE(.clk(clk), .write_enable(re), .r_a(r_a), .r_b(r_b), .write_addr(r_a), .write_data(write_data), .a(a), .b(b));
    ula ULA(.A(a), .B(b_ula), .Seletor(ula_sel), .S(ula_out));
    memoria_dados MED(.writeEnable(we), .endereco(b), .dadoEntrada(a), .clk(clk), .dadoSaida(data_out));

    
endmodule

trabalho1/parte4/redux/redux_TB.v
`timescale 1ps/1ps
module redux_TB ();
reg clk;

redux RED(.clk(clk));

initial begin 
    $dumpfile("redux.vcd");
    $dumpvars(5, redux_TB);
end

initial begin: clock
    clk = 0;
    for (integer i = 0; i < 200; i++) begin
        #10;
        clk = ~clk;
    end
    
    for (reg[7:0] j = 0; j < 255; j++) begin
        $display("data[%d] = %d", j, RED.MED.memoria[j]);
    end
end
    
endmodule

trabalho1/parte4/redux/redux.vcd
$date
	Thu Oct 24 18:53:04 2024
$end
$version
	Icarus Verilog
$end
$timescale
	1ps
$end
$scope module redux_TB $end
$var reg 1 ! clk $end
$scope module RED $end
$var wire 1 ! clk $end
$var wire 1 " zero_flag $end
$var wire 8 # write_data [7:0] $end
$var wire 1 $ we $end
$var wire 4 % ula_sel [3:0] $end
$var wire 8 & ula_out [7:0] $end
$var wire 1 ' se_mx $end
$var wire 1 ( re $end
$var wire 1 ) r_mx $end
$var wire 2 * r_b [1:0] $end
$var wire 2 + r_a [1:0] $end
$var wire 4 , opcode [3:0] $end
$var wire 8 - n_pc [7:0] $end
$var wire 1 . j_mx $end
$var wire 8 / instrucao [7:0] $end
$var wire 8 0 imm_extended [7:0] $end
$var wire 4 1 imm [3:0] $end
$var wire 8 2 data_out [7:0] $end
$var wire 1 3 d_mx $end
$var wire 8 4 cur_pc [7:0] $end
$var wire 8 5 b_ula [7:0] $end
$var wire 1 6 b_mx $end
$var wire 8 7 b [7:0] $end
$var wire 8 8 a [7:0] $end
$scope module BRE $end
$var wire 8 9 a [7:0] $end
$var wire 8 : b [7:0] $end
$var wire 1 ! clk $end
$var wire 2 ; r_a [1:0] $end
$var wire 2 < r_b [1:0] $end
$var wire 2 = write_addr [1:0] $end
$var wire 8 > write_data [7:0] $end
$var wire 1 ( write_enable $end
$upscope $end
$scope module MEC $end
$var wire 4 ? opcode [3:0] $end
$var reg 1 6 b_mx $end
$var reg 1 3 d_mx $end
$var reg 1 . j_mx $end
$var reg 1 ) r_mx $end
$var reg 1 ( re $end
$var reg 1 ' se_mx $end
$var reg 4 @ ula [3:0] $end
$var reg 1 $ we $end
$upscope $end
$scope module MED $end
$var wire 1 ! clk $end
$var wire 8 A dadoEntrada [7:0] $end
$var wire 8 B dadoSaida [7:0] $end
$var wire 8 C endereco [7:0] $end
$var wire 1 $ writeEnable $end
$upscope $end
$scope module MEI $end
$var wire 8 D endereco [7:0] $end
$var reg 8 E instrucao [7:0] $end
$upscope $end
$scope module NPC $end
$var wire 8 F b [7:0] $end
$var wire 1 6 bmx $end
$var wire 8 G imm [7:0] $end
$var wire 1 . jmx $end
$var wire 1 " zero_flag $end
$var wire 8 H pc [7:0] $end
$var wire 8 I curPC [7:0] $end
$upscope $end
$scope module PC $end
$var wire 1 ! clk $end
$var wire 8 J entrada [7:0] $end
$var reg 8 K saida [7:0] $end
$upscope $end
$scope module ULA $end
$var wire 8 L A [7:0] $end
$var wire 8 M B [7:0] $end
$var wire 4 N Seletor [3:0] $end
$var wire 8 O S [7:0] $end
$upscope $end
$upscope $end
$scope begin clock $end
$scope begin $ivl_for_loop0 $end
$var integer 32 P i [31:0] $end
$upscope $end
$scope begin $ivl_for_loop1 $end
$var reg 8 Q j [7:0] $end
$upscope $end
$upscope $end
$upscope $end
$enddefinitions $end
$comment Show the parameter values. $end
$dumpall
$end
#0
$dumpvars
bx Q
b0 P
b0 O
b11 N
b0 M
b0 L
b0 K
b1 J
b0 I
b1 H
b0 G
b0 F
b10110000 E
b0 D
b0 C
bx B
b0 A
b11 @
b1011 ?
b0 >
b0 =
b0 <
b0 ;
b0 :
b0 9
b0 8
b0 7
06
b0 5
b0 4
13
bx 2
b0 1
b0 0
b10110000 /
0.
b1 -
b1011 ,
b0 +
b0 *
0)
1(
0'
b0 &
b11 %
0$
b0 #
1"
0!
$end
#10
b1 +
b1 ;
b1 =
b10 -
b10 H
b10 J
b1 *
b1 <
b101 0
b101 G
b101 1
b10110101 /
b10110101 E
b1 4
b1 D
b1 I
b1 K
b1 P
1!
#20
b10 P
0!
#30
b10 +
b10 ;
b10 =
b11 -
b11 H
b11 J
b10 *
b10 <
b11111010 0
b11111010 G
b1010 1
b10111010 /
b10111010 E
b10 4
b10 D
b10 I
b10 K
b11 P
1!
#40
b100 P
0!
#50
b11 +
b11 ;
b11 =
b100 -
b100 H
b100 J
b11 *
b11 <
b11111111 0
b11111111 G
b1111 1
b10111111 /
b10111111 E
b11 4
b11 D
b11 I
b11 K
b101 P
1!
#60
b110 P
0!
#70
b11 #
b11 >
b11 &
b11 O
b11 5
b11 M
b0 +
b0 ;
b0 =
b100 %
b100 @
b100 N
1'
1)
b101 -
b101 H
b101 J
b11 0
b11 G
b11 1
b100 ,
b100 ?
b1000011 /
b1000011 E
b100 4
b100 D
b100 I
b100 K
b111 P
1!
#80
b1000 P
0!
#90
b11 #
b11 >
b11 &
b11 O
b1 +
b1 ;
b1 =
0'
0)
b110 -
b110 H
b110 J
b11 7
b11 :
b11 C
b11 F
b0 *
b0 <
b100 0
b100 G
b100 1
b1100 ,
b1100 ?
1"
b11000100 /
b11000100 E
b101 4
b101 D
b101 I
b101 K
b0 8
b0 9
b0 A
b0 L
b1001 P
1!
#100
b1010 P
0!
#110
b0 #
b0 >
b0 &
b0 O
b0 +
b0 ;
b0 =
b11 %
b11 @
b11 N
0"
b111 -
b111 H
b111 J
b0 0
b0 G
b0 1
b1011 ,
b1011 ?
b10110000 /
b10110000 E
b11 8
b11 9
b11 A
b11 L
b110 4
b110 D
b110 I
b110 K
b1011 P
1!
#120
b1100 P
0!
#130
b11 #
b11 >
b11 &
b11 O
b1 +
b1 ;
b1 =
0(
1$
b1000 -
b1000 H
b1000 J
b100 0
b100 G
b100 1
b11 ,
b11 ?
0"
b110100 /
b110100 E
b0 5
b0 M
b111 4
b111 D
b111 I
b111 K
b11 8
b11 9
b11 A
b11 L
b0 7
b0 :
b0 C
b0 F
b1101 P
1!
#140
b1110 P
0!
#150
b111 #
b111 >
b111 &
b111 O
1"
b111 5
b111 M
b0 8
b0 9
b0 A
b0 L
b0 +
b0 ;
b0 =
1(
0$
b100 %
b100 @
b100 N
1'
1)
b1001 -
b1001 H
b1001 J
b11 *
b11 <
b111 0
b111 G
b111 1
b100 ,
b100 ?
b1000111 /
b1000111 E
b1000 4
b1000 D
b1000 I
b1000 K
b11 2
b11 B
b1111 P
1!
#160
b10000 P
0!
#170
b1010 #
b1010 >
b1010 &
b1010 O
b11 5
b11 M
b1010 -
b1010 H
b1010 J
b11 0
b11 G
b11 1
0"
b1000011 /
b1000011 E
b1001 4
b1001 D
b1001 I
b1001 K
b111 8
b111 9
b111 A
b111 L
b10001 P
1!
#180
b10010 P
0!
#190
b1010 #
b1010 >
1"
b1010 &
b1010 O
b11 +
b11 ;
b11 =
b1010 5
b1010 M
0'
0)
b1011 -
b1011 H
b1011 J
bx 2
bx B
b1010 7
b1010 :
b1010 C
b1010 F
b0 *
b0 <
b11111100 0
b11111100 G
b1100 1
b1100 ,
b1100 ?
b11001100 /
b11001100 E
b0 8
b0 9
b0 A
b0 L
b1010 4
b1010 D
b1010 I
b1010 K
b10011 P
1!
#200
b10100 P
0!
#210
b1010 #
b1010 >
b1010 &
b1010 O
b10 +
b10 ;
b10 =
b1100 -
b1100 H
b1100 J
b11111000 0
b11111000 G
b1000 1
1"
b11001000 /
b11001000 E
b1011 4
b1011 D
b1011 I
b1011 K
b0 8
b0 9
b0 A
b0 L
b10101 P
1!
#220
b10110 P
0!
#230
b10 #
b10 >
b10 &
b10 O
b11111000 5
b11111000 M
b0 +
b0 ;
b0 =
1'
1)
0"
b1101 -
b1101 H
b1101 J
b100 ,
b100 ?
b1001000 /
b1001000 E
b1010 8
b1010 9
b1010 A
b1010 L
b1100 4
b1100 D
b1100 I
b1100 K
b10111 P
1!
#240
b11000 P
0!
#250
b101000 #
b101000 >
b101000 &
b101000 O
b10 5
b10 M
b10 +
b10 ;
b10 =
b110 %
b110 @
b110 N
0'
0)
b1110 -
b1110 H
b1110 J
b1110 ,
b1110 ?
b11101000 /
b11101000 E
b1101 4
b1101 D
b1101 I
b1101 K
b1010 8
b1010 9
b1010 A
b1010 L
b10 7
b10 :
b10 C
b10 F
b11001 P
1!
#260
b11010 P
0!
#270
b101010 #
b101010 >
b101010 &
b101010 O
b100 %
b100 @
b100 N
b1111 -
b1111 H
b1111 J
b1100 ,
b1100 ?
b11001000 /
b11001000 E
b101000 8
b101000 9
b101000 A
b101000 L
b1110 4
b1110 D
b1110 I
b1110 K
b11011 P
1!
#280
b11100 P
0!
#290
b1 #
b1 >
b1 &
b1 O
b11111111 5
b11111111 M
b0 +
b0 ;
b0 =
1'
1)
b10000 -
b10000 H
b10000 J
b1010 7
b1010 :
b1010 C
b1010 F
b11 *
b11 <
b11111111 0
b11111111 G
b1111 1
b100 ,
b100 ?
b1001111 /
b1001111 E
b1111 4
b1111 D
b1111 I
b1111 K
b10 8
b10 9
b10 A
b10 L
b11101 P
1!
#300
b11110 P
0!
#310
b100010 #
b100010 >
b100010 &
b100010 O
b10 +
b10 ;
b10 =
b11111000 5
b11111000 M
0(
1$
0)
b10001 -
b10001 H
b10001 J
b1 7
b1 :
b1 C
b1 F
b0 *
b0 <
b11111000 0
b11111000 G
b1000 1
b11 ,
b11 ?
b111000 /
b111000 E
b101010 8
b101010 9
b101010 A
b101010 L
b10000 4
b10000 D
b10000 I
b10000 K
b11111 P
1!
#320
b100000 P
0!
#330
b0 #
b0 >
b0 &
b0 O
b1 8
b1 9
b1 A
b1 L
b0 +
b0 ;
b0 =
b1 5
b1 M
1(
0$
b11 %
b11 @
b11 N
0'
b10010 -
b10010 H
b10010 J
b0 0
b0 G
b0 1
b1011 ,
b1011 ?
b10110000 /
b10110000 E
b10001 4
b10001 D
b10001 I
b10001 K
b101010 2
b101010 B
b100001 P
1!
#340
b100010 P
0!
#350
b10 +
b10 ;
b10 =
0"
b10011 -
b10011 H
b10011 J
b10 *
b10 <
b11111010 0
b11111010 G
b1010 1
b101010 5
b101010 M
b10111010 /
b10111010 E
b101010 8
b101010 9
b101010 A
b101010 L
bx 2
bx B
b101010 7
b101010 :
b101010 C
b101010 F
b10010 4
b10010 D
b10010 I
b10010 K
b100011 P
1!
#360
b100100 P
0!
#370
b11111101 #
b11111101 >
b11111101 &
b11111101 O
b101 %
b101 @
b101 N
b10100 -
b10100 H
b10100 J
b1 *
b1 <
b11111001 0
b11111001 G
b1001 1
b1101 ,
b1101 ?
1"
b11011001 /
b11011001 E
b11 5
b11 M
b10011 4
b10011 D
b10011 I
b10011 K
b0 8
b0 9
b0 A
b0 L
bx 2
bx B
b11 7
b11 :
b11 C
b11 F
b100101 P
1!
#380
b100110 P
0!
#390
b101 #
b101 >
b101 &
b101 O
b101 5
b101 M
b0 +
b0 ;
b0 =
b100 %
b100 @
b100 N
1'
1)
1"
b10101 -
b10101 H
b10101 J
b101 0
b101 G
b101 1
b100 ,
b100 ?
b1000101 /
b1000101 E
b0 8
b0 9
b0 A
b0 L
b10100 4
b10100 D
b10100 I
b10100 K
b100111 P
1!
#400
b101000 P
0!
#410
b101000 #
b101000 >
b101000 &
b101000 O
b11 5
b11 M
b110 %
b110 @
b110 N
0'
0)
b10110 -
b10110 H
b10110 J
b1 0
b1 G
b1 1
b1110 ,
b1110 ?
0"
b11100001 /
b11100001 E
b10101 4
b10101 D
b10101 I
b10101 K
b101 8
b101 9
b101 A
b101 L
b101001 P
1!
#420
b101010 P
0!
#430
b0 #
b0 >
b0 &
b0 O
b11111101 5
b11111101 M
0(
1.
b11000 -
b11000 H
b11000 J
b11111101 7
b11111101 :
b11111101 C
b11111101 F
b10 *
b10 <
b10 0
b10 G
b10 1
b1 ,
b1 ?
b10010 /
b10010 E
b101000 8
b101000 9
b101000 A
b101000 L
b10110 4
b10110 D
b10110 I
b10110 K
b101011 P
1!
#440
b101100 P
0!
#450
b101000 #
b101000 >
b101000 &
b101000 O
b0 5
b0 M
1(
b100 %
b100 @
b100 N
1'
1)
0.
b11001 -
b11001 H
b11001 J
b101000 7
b101000 :
b101000 C
b101000 F
b0 *
b0 <
b0 0
b0 G
b0 1
b100 ,
b100 ?
b1000000 /
b1000000 E
b11000 4
b11000 D
b11000 I
b11000 K
b101101 P
1!
#460
b101110 P
0!
#470
b11110101 #
b11110101 >
b11110101 &
b11110101 O
b11111101 8
b11111101 9
b11111101 A
b11111101 L
b10 +
b10 ;
b10 =
b11111000 5
b11111000 M
0(
0)
16
b11010 -
b11010 H
b11010 J
b11111000 0
b11111000 G
b1000 1
b0 ,
b0 ?
b1000 /
b1000 E
b11001 4
b11001 D
b11001 I
b11001 K
b101111 P
1!
#480
b110000 P
0!
#490
b0 #
b0 >
b0 &
b0 O
b11 5
b11 M
1(
0'
06
b11011 -
b11011 H
b11011 J
b11 7
b11 :
b11 C
b11 F
b1 *
b1 <
b11111001 0
b11111001 G
b1001 1
b1100 ,
b1100 ?
b11001001 /
b11001001 E
b11010 4
b11010 D
b11010 I
b11010 K
b110001 P
1!
#500
b110010 P
0!
#510
b0 #
b0 >
b0 &
b0 O
b101000 5
b101000 M
b0 +
b0 ;
b0 =
b11 %
b11 @
b11 N
0"
b11100 -
b11100 H
b11100 J
b101000 7
b101000 :
b101000 C
b101000 F
b0 *
b0 <
b0 0
b0 G
b0 1
b1011 ,
b1011 ?
b10110000 /
b10110000 E
b101000 8
b101000 9
b101000 A
b101000 L
b11011 4
b11011 D
b11011 I
b11011 K
b110011 P
1!
#520
b110100 P
0!
#530
b1010 #
b1010 >
b1010 &
b1010 O
b11 +
b11 ;
b11 =
b100 %
b100 @
b100 N
b11101 -
b11101 H
b11101 J
b10 *
b10 <
b11111110 0
b11111110 G
b1110 1
b1100 ,
b1100 ?
0"
b11001110 /
b11001110 E
b0 5
b0 M
b11100 4
b11100 D
b11100 I
b11100 K
b1010 8
b1010 9
b1010 A
b1010 L
b11 2
b11 B
b0 7
b0 :
b0 C
b0 F
b110101 P
1!
#540
b110110 P
0!
#550
b1 #
b1 >
b1 &
b1 O
1"
b1 5
b1 M
b0 8
b0 9
b0 A
b0 L
b0 +
b0 ;
b0 =
1'
1)
b11110 -
b11110 H
b11110 J
bx 2
bx B
b11 7
b11 :
b11 C
b11 F
b1 *
b1 <
b1 0
b1 G
b1 1
b100 ,
b100 ?
b1000001 /
b1000001 E
b11101 4
b11101 D
b11101 I
b11101 K
b110111 P
1!
#560
b111000 P
0!
#570
b11 #
b11 >
b11 &
b11 O
b10 5
b10 M
0(
1.
b100000 -
b100000 H
b100000 J
b11 2
b11 B
b0 7
b0 :
b0 C
b0 F
b10 *
b10 <
b10 0
b10 G
b10 1
b1 ,
b1 ?
0"
b10010 /
b10010 E
b11110 4
b11110 D
b11110 I
b11110 K
b1 8
b1 9
b1 A
b1 L
b111001 P
1!
#580
b111010 P
0!
#590
b111 &
b111 O
b101010 #
b101010 >
b11 8
b11 9
b11 A
b11 L
b1 +
b1 ;
b1 =
b100 5
b100 M
1(
03
0)
0.
b100001 -
b100001 H
b100001 J
b101010 2
b101010 B
b1 7
b1 :
b1 C
b1 F
b0 *
b0 <
b100 0
b100 G
b100 1
b10 ,
b10 ?
b100100 /
b100100 E
b100000 4
b100000 D
b100000 I
b100000 K
b111011 P
1!
#600
b111100 P
0!
#610
b101010 &
b101010 O
b101010 #
b101010 >
b0 5
b0 M
13
0'
b100010 -
b100010 H
b100010 J
b11 2
b11 B
b0 7
b0 :
b0 C
b0 F
b10 *
b10 <
b110 0
b110 G
b110 1
b1100 ,
b1100 ?
b11000110 /
b11000110 E
b100001 4
b100001 D
b100001 I
b100001 K
b101010 8
b101010 9
b101010 A
b101010 L
b111101 P
1!
#620
b111110 P
0!
#630
b110100 #
b110100 >
b110100 &
b110100 O
b1010 5
b1010 M
0(
1$
b100011 -
b100011 H
b100011 J
bx 2
bx B
b1010 7
b1010 :
b1010 C
b1010 F
b11 *
b11 <
b111 0
b111 G
b111 1
b11 ,
b11 ?
b110111 /
b110111 E
b100010 4
b100010 D
b100010 I
b100010 K
b111111 P
1!
#640
b1000000 P
0!
#650
b1010 #
b1010 >
b1010 &
b1010 O
b0 5
b0 M
b1010 8
b1010 9
b1010 A
b1010 L
b11 +
b11 ;
b11 =
1(
0$
b101 %
b101 @
b101 N
b100100 -
b100100 H
b100100 J
b0 7
b0 :
b0 C
b0 F
b10 *
b10 <
b11111110 0
b11111110 G
b1110 1
b1101 ,
b1101 ?
b11011110 /
b11011110 E
b100011 4
b100011 D
b100011 I
b100011 K
b11 2
b11 B
b1000001 P
1!
#660
b1000010 P
0!
#670
b1 #
b1 >
b1 &
b1 O
1"
b1 5
b1 M
b0 8
b0 9
b0 A
b0 L
b10 +
b10 ;
b10 =
b100 %
b100 @
b100 N
b100101 -
b100101 H
b100101 J
b101010 2
b101010 B
b1 7
b1 :
b1 C
b1 F
b0 *
b0 <
b11111000 0
b11111000 G
b1000 1
b1100 ,
b1100 ?
b11001000 /
b11001000 E
b100100 4
b100100 D
b100100 I
b100100 K
b1000011 P
1!
#680
b1000100 P
0!
#690
b0 #
b0 >
b0 &
b0 O
b0 +
b0 ;
b0 =
b11 %
b11 @
b11 N
b100110 -
b100110 H
b100110 J
b0 0
b0 G
b0 1
b1011 ,
b1011 ?
0"
b10110000 /
b10110000 E
b100101 4
b100101 D
b100101 I
b100101 K
b1 8
b1 9
b1 A
b1 L
b1000101 P
1!
#700
b1000110 P
0!
#710
b101010 &
b101010 O
b11 #
b11 >
b1 +
b1 ;
b1 =
03
0"
b100111 -
b100111 H
b100111 J
b100 0
b100 G
b100 1
b10 ,
b10 ?
b0 5
b0 M
b100100 /
b100100 E
b101010 8
b101010 9
b101010 A
b101010 L
b11 2
b11 B
b0 7
b0 :
b0 C
b0 F
b100110 4
b100110 D
b100110 I
b100110 K
b1000111 P
1!
#720
b1001000 P
0!
#730
b1 &
b1 O
b10 +
b10 ;
b10 =
0(
1.
b11111 -
b11111 H
b11111 J
b11111000 0
b11111000 G
b1000 1
b1 ,
b1 ?
b11000 /
b11000 E
b100111 4
b100111 D
b100111 I
b100111 K
b1 8
b1 9
b1 A
b1 L
b1001001 P
1!
#740
b1001010 P
0!
#750
b10111 -
b10111 H
b10111 J
b11111 4
b11111 D
b11111 I
b11111 K
b1001011 P
1!
#760
b1001100 P
0!
#770
b1010 &
b1010 O
b1010 8
b1010 9
b1010 A
b1010 L
b11 +
b11 ;
b11 =
b10011 -
b10011 H
b10011 J
b11111100 0
b11111100 G
b1100 1
b11100 /
b11100 E
b10111 4
b10111 D
b10111 I
b10111 K
b1001101 P
1!
#780
b1001110 P
0!
#790
b11111110 &
b11111110 O
b11111110 #
b11111110 >
b11 5
b11 M
b1 8
b1 9
b1 A
b1 L
b10 +
b10 ;
b10 =
1(
b101 %
b101 @
b101 N
13
0.
b10100 -
b10100 H
b10100 J
bx 2
bx B
b11 7
b11 :
b11 C
b11 F
b1 *
b1 <
b11111001 0
b11111001 G
b1001 1
b1101 ,
b1101 ?
b11011001 /
b11011001 E
b10011 4
b10011 D
b10011 I
b10011 K
b1001111 P
1!
#800
b1010000 P
0!
#810
b101 #
b101 >
b101 &
b101 O
1"
b101 5
b101 M
b0 +
b0 ;
b0 =
b100 %
b100 @
b100 N
1'
1)
b10101 -
b10101 H
b10101 J
b101 0
b101 G
b101 1
b100 ,
b100 ?
b1000101 /
b1000101 E
b10100 4
b10100 D
b10100 I
b10100 K
b0 8
b0 9
b0 A
b0 L
b1010001 P
1!
#820
b1010010 P
0!
